django_intram/__init__.py
django_intram/apps.py
django_intram/intram.py
django_intram/urls.py
django_intram/views.py
django_intram-0.1.1.dist-info/LICENSE
django_intram-0.1.1.dist-info/METADATA
django_intram-0.1.1.dist-info/WHEEL
django_intram-0.1.1.dist-info/top_level.txt
django_intram-0.1.1.dist-info/RECORD
